latexify/__init__.py
latexify/_version.py
latexify/analyzers.py
latexify/ast_utils.py
latexify/config.py
latexify/exceptions.py
latexify/frontend.py
latexify/generate_latex.py
latexify/ipython_wrappers.py
latexify/parser.py
latexify/test_utils.py
latexify/codegen/__init__.py
latexify/codegen/algorithmic_codegen.py
latexify/codegen/codegen_utils.py
latexify/codegen/expression_codegen.py
latexify/codegen/expression_rules.py
latexify/codegen/function_codegen.py
latexify/codegen/identifier_converter.py
latexify/codegen/latex.py
latexify/transformers/__init__.py
latexify/transformers/assignment_reducer.py
latexify/transformers/aug_assign_replacer.py
latexify/transformers/docstring_remover.py
latexify/transformers/function_expander.py
latexify/transformers/identifier_replacer.py
latexify/transformers/prefix_trimmer.py
latexify_py-0.4.3.post1.dist-info/METADATA
latexify_py-0.4.3.post1.dist-info/WHEEL
latexify_py-0.4.3.post1.dist-info/licenses/LICENSE
latexify_py-0.4.3.post1.dist-info/RECORD
